mockify/__init__.py
mockify/_compat/__init__.py
mockify/_compat/asyncio.py
mockify/_globals.py
mockify/_utils.py
mockify/abc.py
mockify/actions.py
mockify/api.py
mockify/cardinality.py
mockify/core/__init__.py
mockify/core/_call.py
mockify/core/_config.py
mockify/core/_expectation.py
mockify/core/_functions.py
mockify/core/_inspect.py
mockify/core/_session.py
mockify/exc.py
mockify/matchers.py
mockify/mock/__init__.py
mockify/mock/_abc_mock.py
mockify/mock/_base.py
mockify/mock/_factory.py
mockify/mock/_function.py
mockify/mock/_mock.py
mockify-0.14.0.dist-info/LICENSE
mockify-0.14.0.dist-info/METADATA
mockify-0.14.0.dist-info/WHEEL
mockify-0.14.0.dist-info/RECORD
