Metadata-Version: 2.1
Name: mockify
Version: 0.14.0
Summary: Highly customizable and expressive mocking library for Python.
License: MIT
Author: Maciej Wiatrzyk
Author-email: maciej.wiatrzyk@gmail.com
Requires-Python: >=3.8,<4.0
Classifier: License :: OSI Approved :: MIT License
Classifier: Programming Language :: Python :: 3
Classifier: Programming Language :: Python :: 3.8
Classifier: Programming Language :: Python :: 3.9
Classifier: Programming Language :: Python :: 3.10
Classifier: Programming Language :: Python :: 3.11
Classifier: Programming Language :: Python :: 3.12
